pod5_format_tools/__init__.py
pod5_format_tools/_version.py
pod5_format_tools/pod5_convert_from_fast5.py
pod5_format_tools/pod5_convert_to_fast5.py
pod5_format_tools/pod5_demux.py
pod5_format_tools/pod5_inspect.py
pod5_format_tools/pod5_merge.py
pod5_format_tools/pod5_repack.py
pod5_format_tools/pod5_update.py
pod5_format_tools/utils.py
pod5_format_tools-0.0.41.dist-info/METADATA
pod5_format_tools-0.0.41.dist-info/WHEEL
pod5_format_tools-0.0.41.dist-info/entry_points.txt
pod5_format_tools-0.0.41.dist-info/top_level.txt
pod5_format_tools-0.0.41.dist-info/RECORD
